cmonge/__init__.py
cmonge/datasets/__init__.py
cmonge/datasets/conditional_loader.py
cmonge/datasets/single_loader.py
cmonge/evaluate.py
cmonge/metrics.py
cmonge/models/__init__.py
cmonge/models/embedding.py
cmonge/models/nn.py
cmonge/models/rdkit.py
cmonge/tests/__init__.py
cmonge/tests/configs/synthetic.yml
cmonge/tests/configs/test.h5ad
cmonge/tests/conftest.py
cmonge/tests/datasets/__init__.py
cmonge/tests/datasets/test_conditional_loader.py
cmonge/tests/datasets/test_single_loader.py
cmonge/tests/test_imports.py
cmonge/trainers/__init__.py
cmonge/trainers/ae_trainer.py
cmonge/trainers/conditional_monge_trainer.py
cmonge/trainers/conditional_trainer.py
cmonge/trainers/ot_trainer.py
cmonge/utils.py
cmonge-0.1.2.dist-info/LICENSE
cmonge-0.1.2.dist-info/METADATA
cmonge-0.1.2.dist-info/WHEEL
cmonge-0.1.2.dist-info/RECORD
