Metadata-Version: 2.3
Name: cmonge
Version: 0.1.2
Summary: Extension of the Monge Gap to learn conditional optimal transport maps
Keywords: Machine Learning,Optimal Transport,Neural OT,Monge Gap,Conditional Distribution Learning
Author: Alice Driessen
Author-email: adr@zurich.ibm.com
Requires-Python: >=3.10,<3.12
Classifier: Development Status :: 4 - Beta
Classifier: Intended Audience :: Developers
Classifier: Intended Audience :: Science/Research
Classifier: License :: OSI Approved :: MIT License
Classifier: Programming Language :: Python :: 3
Classifier: Programming Language :: Python :: 3.10
Classifier: Programming Language :: Python :: 3.11
Classifier: Topic :: Scientific/Engineering :: Artificial Intelligence
Requires-Dist: anndata (>=0.10.5.post1,<0.11.0)
Requires-Dist: black (>=24.4.2,<25.0.0)
Requires-Dist: chex (>=0.1.85,<0.2.0)
Requires-Dist: dotmap (>=1.3.30,<2.0.0)
Requires-Dist: flax (>=0.10.2,<0.11.0)
Requires-Dist: isort (>=5.13.2,<6.0.0)
Requires-Dist: jax (>=0.4.36,<0.5.0)
Requires-Dist: jaxlib (>=0.4.36,<0.5.0)
Requires-Dist: loguru (>=0.7.2,<0.8.0)
Requires-Dist: optax (>=0.2.4,<0.3.0)
Requires-Dist: optuna (>=3.5.0,<4.0.0)
Requires-Dist: ott-jax (>=0.5.0,<0.6.0)
Requires-Dist: pandas (>=2.0.0,<3.0.0)
Requires-Dist: rdkit (>=2023.9.5,<2024.0.0)
Requires-Dist: ruff (>=0.5.4,<0.6.0)
Requires-Dist: scanpy (>=1.9.8,<2.0.0)
Requires-Dist: scikit-learn (>=1.4.0,<2.0.0)
Requires-Dist: scipy (==1.12.0)
Requires-Dist: seaborn (>=0.13.2,<0.14.0)
Requires-Dist: typer (>=0.9.0,<0.10.0)
Requires-Dist: types-pyyaml (>=6.0.12.20240311,<7.0.0.0)
Requires-Dist: umap-learn (>=0.5.5,<0.6.0)
Project-URL: Homepage, https://github.com/AI4SCR/conditional-monge
Project-URL: Repository, https://github.com/AI4SCR/conditional-monge
